hardware_api/__init__.py
hardware_api/hardware_api.py
hardware_api/hardware_api_cli.py
hardware_api_client-0.0.6.dist-info/LICENSE
hardware_api_client-0.0.6.dist-info/METADATA
hardware_api_client-0.0.6.dist-info/WHEEL
hardware_api_client-0.0.6.dist-info/top_level.txt
hardware_api_client-0.0.6.dist-info/RECORD
